activate/__init__.py
activate/activity.py
activate/activity_list.py
activate/activity_types.py
activate/files.py
activate/geometry.py
activate/load_activity.py
activate/number_formats.py
activate/serialise.py
activate/times.py
activate/track.py
activate/units.py
activate/app/__init__.py
activate/app/activity_summary.py
activate/app/activity_view.py
activate/app/charts.py
activate/app/checklist.py
activate/app/connect.py
activate/app/maps.py
activate/app/paths.py
activate/app/photos.py
activate/app/settings.py
activate/app/social_tree.py
activate/app/summary.py
activate/app/tables.py
activate/app/widgets.py
activate/app/dialogs/__init__.py
activate/app/dialogs/activity.py
activate/app/dialogs/settings.py
activate/app/sync/__init__.py
activate/app/sync/strava.py
activate/app/sync/strava_export.py
activate/app/ui/__init__.py
activate/app/ui/activity_summary.py
activate/app/ui/activity_view.py
activate/app/ui/main.py
activate/app/ui/settings.py
activate/app/ui/summary.py
activate/filetypes/__init__.py
activate/filetypes/fit.py
activate/filetypes/gpx.py
activate/filetypes/load_xml.py
activate/filetypes/tcx.py
activate/resources/__init__.py
activate/resources/init.sql
activate/resources/__pycache__/__init__.cpython-39.pyc
activate/resources/icons/icon.png
activate/resources/icons/icon.svg
activate/resources/icons/icon_cropped.png
activate/resources/ui/activity_summary.ui
activate/resources/ui/activity_view.ui
activate/resources/ui/main.ui
activate/resources/ui/settings.ui
activate/resources/ui/summary.ui
activate/server/__init__.py
Activate_App-0.0.10.dist-info/LICENCE
Activate_App-0.0.10.dist-info/METADATA
Activate_App-0.0.10.dist-info/WHEEL
Activate_App-0.0.10.dist-info/entry_points.txt
Activate_App-0.0.10.dist-info/top_level.txt
Activate_App-0.0.10.dist-info/RECORD
