Metadata-Version: 2.1
Name: Activate-App
Version: 0.0.10
Summary: Activate is a free activity log and analysis tool.
Home-page: https://gitlab.com/Tom_Fryers/activate
Author: Tom Fryers
License: UNKNOWN
Platform: UNKNOWN
Classifier: Development Status :: 3 - Alpha
Classifier: License :: OSI Approved :: GNU Affero General Public License v3 or later (AGPLv3+)
Classifier: Natural Language :: English
Classifier: Operating System :: OS Independent
Classifier: Programming Language :: Python :: 3
Requires-Python: >=3.7
License-File: LICENCE
Requires-Dist: dtw-python
Provides-Extra: app
Requires-Dist: PyQt5 ; extra == 'app'
Requires-Dist: PyQtChart ; extra == 'app'
Requires-Dist: PyQtWebEngine ; extra == 'app'
Requires-Dist: pyqtlet ; extra == 'app'
Requires-Dist: Markdown ; extra == 'app'
Requires-Dist: fitparse ; extra == 'app'
Requires-Dist: requests ; extra == 'app'
Requires-Dist: beautifulsoup4 ; extra == 'app'
Provides-Extra: server
Requires-Dist: flask ; extra == 'server'
